ICGC_data_parser/__init__.py
ICGC_data_parser/ssm_reader.py
ICGC_data_parser-0.2.2.dist-info/DESCRIPTION.rst
ICGC_data_parser-0.2.2.dist-info/METADATA
ICGC_data_parser-0.2.2.dist-info/RECORD
ICGC_data_parser-0.2.2.dist-info/WHEEL
ICGC_data_parser-0.2.2.dist-info/metadata.json
ICGC_data_parser-0.2.2.dist-info/top_level.txt
