Metadata-Version: 2.0
Name: ICGC-data-parser
Version: 0.2.2
Summary: Tools to facilitate the parsing of SSM data from the International Cancer Genome Consortium data releases, in particular, the simple somatic mutation aggregates.
Home-page: https://github.com/Ad115/ICGC-data-parser
Author: Ad115
Author-email: a.garcia230395@gmail.com
License: UNKNOWN
Project-URL: Say Thanks!, https://saythanks.io/to/Ad115
Project-URL: Documentation, https://icgc-data-parser.readthedocs.io
Project-URL: Source, https://github.com/Ad115/ICGC-data-parser/
Project-URL: Author, https://agargar.wordpress.com/
Keywords: vcf data mutations icgc parsing
Platform: UNKNOWN
Classifier: Development Status :: 3 - Alpha
Classifier: Intended Audience :: Information Technology
Classifier: Intended Audience :: Science/Research
Classifier: Intended Audience :: Education
Classifier: Intended Audience :: Developers
Classifier: Topic :: Scientific/Engineering :: Artificial Life
Classifier: Topic :: Scientific/Engineering :: Bio-Informatics
Classifier: Topic :: Scientific/Engineering :: Medical Science Apps.
Classifier: License :: OSI Approved :: MIT License
Classifier: Programming Language :: Python :: 3 :: Only
Provides-Extra: dev
Requires-Dist: pyvcf
Provides-Extra: dev
Requires-Dist: jupyter; extra == 'dev'
Requires-Dist: matplotlib; extra == 'dev'
Requires-Dist: numpy; extra == 'dev'
Requires-Dist: seaborn; extra == 'dev'
Requires-Dist: scipy; extra == 'dev'
